MANIFEST.in
README.md
requirements.txt
setup.cfg
setup.py
brayns/__init__.py
brayns/version.py
brayns.egg-info/PKG-INFO
brayns.egg-info/SOURCES.txt
brayns.egg-info/dependency_links.txt
brayns.egg-info/requires.txt
brayns.egg-info/top_level.txt
brayns/core/__init__.py
brayns/core/application.py
brayns/core/camera.py
brayns/core/camera_controller.py
brayns/core/color_ramp.py
brayns/core/coloring.py
brayns/core/entrypoint.py
brayns/core/framebuffer.py
brayns/core/gbuffer_exporter.py
brayns/core/geometry.py
brayns/core/image.py
brayns/core/light.py
brayns/core/loader.py
brayns/core/material.py
brayns/core/model.py
brayns/core/near_clip.py
brayns/core/opacity_curve.py
brayns/core/pick.py
brayns/core/projection.py
brayns/core/region.py
brayns/core/renderer.py
brayns/core/simulation.py
brayns/core/snapshot.py
brayns/core/version.py
brayns/core/view.py
brayns/movie/__init__.py
brayns/movie/movie.py
brayns/movie/movie_frames.py
brayns/network/__init__.py
brayns/network/client.py
brayns/network/connector.py
brayns/network/future.py
brayns/network/instance.py
brayns/network/listener.py
brayns/network/logger.py
brayns/network/jsonrpc/__init__.py
brayns/network/jsonrpc/json_rpc_dispatcher.py
brayns/network/jsonrpc/json_rpc_error.py
brayns/network/jsonrpc/json_rpc_future.py
brayns/network/jsonrpc/json_rpc_handler.py
brayns/network/jsonrpc/json_rpc_listener.py
brayns/network/jsonrpc/json_rpc_manager.py
brayns/network/jsonrpc/json_rpc_progress.py
brayns/network/jsonrpc/json_rpc_reply.py
brayns/network/jsonrpc/json_rpc_request.py
brayns/network/jsonrpc/json_rpc_task.py
brayns/network/jsonrpc/json_rpc_tasks.py
brayns/network/websocket/__init__.py
brayns/network/websocket/async_web_socket.py
brayns/network/websocket/errors.py
brayns/network/websocket/event_loop.py
brayns/network/websocket/web_socket.py
brayns/network/websocket/web_socket_client.py
brayns/network/websocket/web_socket_connector.py
brayns/network/websocket/web_socket_listener.py
brayns/plugins/__init__.py
brayns/plugins/atlas.py
brayns/plugins/bbp.py
brayns/plugins/cell_placement.py
brayns/plugins/circuit.py
brayns/plugins/cylindric_camera.py
brayns/plugins/dti.py
