Metadata-Version: 2.1
Name: brayns
Version: 3.10.1
Summary: Brayns Python API
Home-page: https://github.com/BlueBrain/Brayns
Author: Blue Brain Project
Author-email: bbp-open-source@googlegroups.com
License: LGPLv3
Download-URL: https://github.com/BlueBrain/Brayns
Project-URL: Tracker, https://bbpteam.epfl.ch/project/issues/projects/BRAYNS/issues
Project-URL: Source, https://github.com/BlueBrain/Brayns
Keywords: brayns,raytracing,bbp,BlueBrain
Platform: UNKNOWN
Classifier: Development Status :: 4 - Beta
Classifier: License :: OSI Approved :: GNU Lesser General Public License v3 (LGPLv3)
Classifier: Operating System :: OS Independent
Classifier: Programming Language :: Python :: 3.9
Classifier: Topic :: Software Development :: Libraries
Classifier: Topic :: Software Development :: Libraries :: Python Modules
Requires-Python: >=3.9
